MANIFEST.in
README.md
setup.cfg
setup.py
structure_me/__init__.py
structure_me/helper_functions.py
structure_me/structure_me.py
structure_me.egg-info/PKG-INFO
structure_me.egg-info/SOURCES.txt
structure_me.egg-info/dependency_links.txt
structure_me.egg-info/entry_points.txt
structure_me.egg-info/top_level.txt
structure_me/data/sample_readme.md
structure_me/data/sample_setup.cfg
structure_me/data/sample_setup.py
tests/__init__.py
tests/test_base.py
tests/test_files.py
tests/test_folders.py
tests/test_main.py