Metadata-Version: 2.1
Name: structure-me
Version: 1.7
Summary: Create a boilerplate folder and file structure for python projects.
Home-page: https://github.com/marcospaterson/structure_me
Author: Marcos Paterson
Author-email: marcos.paterson@gmail.com
License: UNKNOWN
Project-URL: Bug Reports, https://github.com/the-marcos/structure_me/issues
Project-URL: Funding, https://github.com/the-marcos
Project-URL: Say Thanks!, https://github.com/the-marcos
Project-URL: Source, https://github.com/the-marcos/structure_me
Keywords: setuptools development folder template structure packaging
Platform: UNKNOWN
Classifier: Development Status :: 5 - Production/Stable
Classifier: Intended Audience :: Developers
Classifier: Topic :: Software Development
Classifier: License :: OSI Approved :: MIT License
Classifier: Programming Language :: Python :: 3
Classifier: Programming Language :: Python :: 3.5
Classifier: Programming Language :: Python :: 3.6
Classifier: Programming Language :: Python :: 3.7
Classifier: Programming Language :: Python :: 3.8
Classifier: Programming Language :: Python :: 3 :: Only
Requires-Python: >=3.5, <4
